fugo/__init__.py
fugo/chord.py
fugo/duration.py
fugo/interval.py
fugo/key.py
fugo/meter.py
fugo/motion.py
fugo/note.py
fugo/time.py
fugo-0.0.4.dist-info/LICENSE
fugo-0.0.4.dist-info/METADATA
fugo-0.0.4.dist-info/WHEEL
fugo-0.0.4.dist-info/top_level.txt
fugo-0.0.4.dist-info/RECORD
