Metadata-Version: 2.1
Name: fugo
Version: 0.0.4
Summary: Counterpoint for Python
Author-email: Ujan RoyBandyopadhyay <ujan.roybandyopadhyay@gmail.com>
License: MIT License
Project-URL: Source, https://github.com/ujan-r/fugo
Keywords: music,midi,counterpoint
Classifier: Development Status :: 4 - Beta
Classifier: License :: OSI Approved :: MIT License
Classifier: Operating System :: OS Independent
Classifier: Programming Language :: Python
Classifier: Programming Language :: Python :: 3
Classifier: Programming Language :: Python :: 3 :: Only
Classifier: Programming Language :: Python :: 3.11
Classifier: Programming Language :: Python :: 3.12
Classifier: Typing :: Typed
Requires-Python: ~=3.11
License-File: LICENSE
